featurizer_api_client/__init__.py
featurizer_api_client/client.py
featurizer_api_client/common/__init__.py
featurizer_api_client/common/exceptions.py
featurizer_api_client/common/logging.py
featurizer_api_client/utils/__init__.py
featurizer_api_client/utils/data.py
featurizer_api_client/utils/headers.py
featurizer_api_client-1.0.1.dist-info/LICENSE
featurizer_api_client-1.0.1.dist-info/METADATA
featurizer_api_client-1.0.1.dist-info/WHEEL
featurizer_api_client-1.0.1.dist-info/top_level.txt
featurizer_api_client-1.0.1.dist-info/RECORD
