Metadata-Version: 2.1
Name: featurizer-api-client
Version: 1.0.1
Summary: Featurizer API client
Home-page: https://github.com/BDALab/featurizer-api-client
Author: Brain Diseases Analysis Laboratory
Author-email: galaz@vut.cz
License: MIT
Platform: UNKNOWN
Classifier: License :: OSI Approved :: MIT License
Classifier: Programming Language :: Python
Classifier: Programming Language :: Python :: 3.7
Classifier: Programming Language :: Python :: 3.8
Classifier: Programming Language :: Python :: 3.9
Classifier: Programming Language :: Python :: 3.10
Classifier: Programming Language :: Python :: Implementation :: PyPy
Classifier: Operating System :: OS Independent
Requires-Python: >=3.7
License-File: LICENSE
Requires-Dist: numpy
Requires-Dist: requests
Requires-Dist: json-tricks
